{
  "RootCommand.Description": "UnifiWatch - Surveille la disponibilité des produits Ubiquiti",
  "StockOption.Description": "Obtenir l'état actuel des stocks",
  "WaitOption.Description": "Attendre que les produits soient en stock",
  "StoreOption.Description": "Boutique à vérifier (Europe, USA, UK) - utilise l'API GraphQL",
  "LegacyApiStoreOption.Description": "Boutique à vérifier (Brésil, Inde, Japon, Taïwan, Singapour, Mexique, Chine) - utilise l'API Shopify",
  "CollectionsOption.Description": "Collections à filtrer (optionnel)",
  "ProductNamesOption.Description": "Noms de produits à surveiller",
  "ProductSkusOption.Description": "SKU de produits à surveiller",
  "SecondsOption.Description": "Intervalle de vérification en secondes",
  "NoWebsiteOption.Description": "Ne pas ouvrir le site Web lorsque le produit est en stock",
  "NoSoundOption.Description": "Ne pas jouer de son lorsque le produit est en stock",
  "LanguageOption.Description": "Forcer la langue/culture (ex: fr-CA, de-DE, es-ES)",
  "Help.UsageHeader": "Utilisation",
  "Help.OptionsHeader": "Options",
  "Help.ExamplesHeader": "Exemples",
  "Help.Example1": "unifiwatch --stock --store USA",
  "Help.Example2": "unifiwatch --wait --seconds 60 --product-skus UDM-SE,U6-Enterprise",
  "List.FoundProducts": "{0} produits trouvés :",
  "List.Headers.Name": "Nom",
  "List.Headers.Available": "Disponibilité",
  "List.Headers.Category": "Catégorie",
  "List.Headers.SKU": "SKU",
  "List.Headers.Price": "Prix",
  "List.InStock": "✓ En stock",
  "List.OutOfStock": "✗ En rupture",
  "List.PriceNA": "S/O",
  "List.CategoryNA": "S/O",
  "List.SKUNA": "S/O",
  "Monitor.MonitoringFor": "Surveillance de : {0}",
  "Monitor.CheckingStock": "Vérification des stocks...",
  "Monitor.CheckingStockDone": "Vérification terminée, pause de {0} secondes",
  "Monitor.MonitoringCancelled": "Surveillance des stocks annulée.",
  "Store.GettingProducts": "Récupération des produits Unifi de la boutique {0}...",
  "Store.RetrievedProducts": "{0} produits récupérés",
  "ConfigWizard.Welcome": "Bienvenue dans l'assistant de configuration UnifiWatch",
  "ConfigWizard.SelectStore": "Quelle boutique Ubiquiti voulez-vous surveiller?",
  "ConfigWizard.ProductFilters": "Filtres de produit (optionnel - laissez vide pour tout surveiller)",
  "ConfigWizard.ProductNames": "Noms de produits à surveiller (séparés par des virgules, Enter pour passer)",
  "ConfigWizard.ProductSkus": "SKU de produits à surveiller (ex. UDM-SE, séparés par des virgules, Enter pour passer)",
  "ConfigWizard.CheckInterval": "Fréquence de vérification du stock? (en secondes, 30-3600)",
  "ConfigWizard.Notifications": "Comment souhaitez-vous être averti quand un stock est disponible?",
  "ConfigWizard.EnableEmail": "Envoyer des notifications par courriel?",
  "ConfigWizard.EnableSms": "Envoyer des notifications par SMS?",
  "ConfigWizard.DedupeWindow": "Temps d'attente avant de répéter la même notification? (en minutes, 1-60)",
  "ConfigWizard.SelectLanguage": "Quelle langue souhaitez-vous utiliser?",
  "ConfigWizard.Saving": "Enregistrement de la configuration...",
  "ConfigWizard.Saved": "Configuration enregistrée avec succès",
  "ConfigWizard.Summary": "Résumé de la configuration:",
  "ConfigWizard.Store": "Boutique",
  "ConfigWizard.CheckIntervalLabel": "Intervalle de vérification",
  "ConfigWizard.EmailEnabled": "Courriel activé",
  "ConfigWizard.SmsEnabled": "SMS activé",
  "ConfigWizard.Error": "Erreur de configuration : {0}",
  "ConfigWizard.EmailConfig": "Paramètres courriel",
  "ConfigWizard.SmtpServer": "Adresse du serveur SMTP (ex. smtp.gmail.com)",
  "ConfigWizard.SmtpPort": "Port SMTP (habituellement 587 pour TLS, 465 pour SSL)",
  "ConfigWizard.UseTls": "Utiliser le chiffrement TLS pour les courriels?",
  "ConfigWizard.FromAddress": "Adresse d'expédition (généralement votre courriel)",
  "ConfigWizard.Recipients": "Destinataires courriel (séparés par des virgules)",
  "ConfigWizard.EmailPassword": "Mot de passe ou mot de passe d'application (saisie masquée)",
  "ConfigWizard.CredentialStored": "Identifiants enregistrés",
  "ConfigWizard.SmsConfig": "Paramètres SMS",
  "ConfigWizard.SmsProvider": "Quel fournisseur SMS utilisez-vous?",
  "ConfigWizard.PhoneNumbers": "Numéros pour SMS (séparés par des virgules, inclure l'indicatif comme +1)",
  "ConfigWizard.AuthToken": "SID de compte Twilio ou jeton API (saisie masquée)",
  "ConfigWizard.InvalidChoice": "Choix invalide, veuillez réessayer",
  "ConfigWizard.InvalidNumber": "Veuillez entrer un nombre entre {0} et {1}",
  "ConfigWizard.AuthMethod": "Quel mode d'authentification courriel utilisez-vous?",
  "ConfigWizard.AuthMethod.Smtp": "SMTP (nom d'utilisateur/mot de passe ou mot de passe d'application)",
  "ConfigWizard.AuthMethod.OAuth": "OAuth 2.0 (Microsoft Graph)",
  "ConfigWizard.SmtpSettings": "Paramètres courriel SMTP",
  "ConfigWizard.OAuthSettings": "Paramètres courriel OAuth 2.0 (Microsoft Graph)",
  "ConfigWizard.OAuthInfo": "Nécessite une appli Azure AD avec l'autorisation d'application Mail.Send (consentement administrateur)",
  "ConfigWizard.OAuthTenantId": "ID de locataire Azure AD (GUID)",
  "ConfigWizard.OAuthClientId": "ID d'application (client)",
  "ConfigWizard.OAuthMailbox": "Adresse de boîte aux lettres (boîte partagée ou compte de service)",
  "ConfigWizard.OAuthClientSecret": "Secret client (saisie masquée)",
  "ConfigWizard.OAuthSecretStored": "Secret client OAuth enregistré"
}
